gen_lambda/__init__.py
gen_lambda/__main__.py
gen_lambda/cli.py
gen_lambda/create_lambda.py
gen_lambda/publish_lambda.py
gen_lambda/remove_lambda.py
gen_lambda/templates/go(provided.al2)/.gitignore.template
gen_lambda/templates/go(provided.al2)/cmd/handler/main.go
gen_lambda/templates/go(provided.al2)/internal/.keep
gen_lambda/templates/go(provided.al2023)/.gitignore.template
gen_lambda/templates/go(provided.al2023)/cmd/handler/main.go
gen_lambda/templates/go(provided.al2023)/internal/.keep
gen_lambda/templates/infra/main.tf
gen_lambda/templates/infra/role.tf
gen_lambda/templates/infra/variables.tf
gen_lambda/templates/nodejs18.x/.env
gen_lambda/templates/nodejs18.x/.gitignore.template
gen_lambda/templates/nodejs18.x/package-lock.json
gen_lambda/templates/nodejs18.x/package.json
gen_lambda/templates/nodejs18.x/src/lambda.ts
gen_lambda/templates/nodejs18.x/src/use_cases/.keep
gen_lambda/templates/nodejs18.x/tsconfig.json
gen_lambda/templates/nodejs20.x/.env
gen_lambda/templates/nodejs20.x/.gitignore.template
gen_lambda/templates/nodejs20.x/package-lock.json
gen_lambda/templates/nodejs20.x/package.json
gen_lambda/templates/nodejs20.x/src/lambda.ts
gen_lambda/templates/nodejs20.x/src/use_cases/.keep
gen_lambda/templates/nodejs20.x/tsconfig.json
gen_lambda/templates/nodejs22.x/.env
gen_lambda/templates/nodejs22.x/.gitignore.template
gen_lambda/templates/nodejs22.x/package-lock.json
gen_lambda/templates/nodejs22.x/package.json
gen_lambda/templates/nodejs22.x/src/lambda.ts
gen_lambda/templates/nodejs22.x/src/use_cases/.keep
gen_lambda/templates/nodejs22.x/tsconfig.json
gen_lambda/templates/python3.11/.env
gen_lambda/templates/python3.11/.gitignore.template
gen_lambda/templates/python3.11/__init__.py
gen_lambda/templates/python3.11/lambda_function.py
gen_lambda/templates/python3.11/requirements.txt
gen_lambda/templates/python3.11/src/__init__.py
gen_lambda/templates/python3.11/src/bootstrap.py
gen_lambda/templates/python3.11/src/use_cases/__init__.py
gen_lambda-0.1.5.dist-info/METADATA
gen_lambda-0.1.5.dist-info/WHEEL
gen_lambda-0.1.5.dist-info/entry_points.txt
gen_lambda-0.1.5.dist-info/RECORD
