Metadata-Version: 2.3
Name: gen_lambda
Version: 0.1.5
Summary: Create/Publish AWS Lambda CLI
License: MIT
Author: Mikhail Dorokhovich
Requires-Python: >=3.11,<4.0
Classifier: License :: OSI Approved :: MIT License
Classifier: Programming Language :: Python :: 3
Classifier: Programming Language :: Python :: 3.11
Classifier: Programming Language :: Python :: 3.12
Classifier: Programming Language :: Python :: 3.13
Requires-Dist: inquirerpy (==0.3.4)
Requires-Dist: typer (==0.15.1)
